hylite/__init__.py
hylite/hycloud.py
hylite/hycollection.py
hylite/hydata.py
hylite/hyfeature.py
hylite/hyheader.py
hylite/hyimage.py
hylite/hylibrary.py
hylite/hyscene.py
hylite/multiprocessing.py
hylite/analyse/__init__.py
hylite/analyse/dtree.py
hylite/analyse/indices.py
hylite/analyse/mwl.py
hylite/analyse/sam.py
hylite/analyse/supervised.py
hylite/analyse/unmixing.py
hylite/analyse/unsupervised.py
hylite/correct/__init__.py
hylite/correct/detrend.py
hylite/correct/equalize.py
hylite/correct/panel.py
hylite/correct/illumination/__init__.py
hylite/correct/illumination/occlusion.py
hylite/correct/illumination/path.py
hylite/correct/illumination/reflection.py
hylite/filter/__init__.py
hylite/filter/combine.py
hylite/filter/dimension_reduction.py
hylite/filter/sample.py
hylite/filter/segment.py
hylite/filter/tpt.py
hylite/io/__init__.py
hylite/io/cameras.py
hylite/io/clouds.py
hylite/io/headers.py
hylite/io/images.py
hylite/io/libraries.py
hylite/io/pmaps.py
hylite/project/__init__.py
hylite/project/align.py
hylite/project/basic.py
hylite/project/camera.py
hylite/project/pmap.py
hylite/project/pushbroom.py
hylite/reference/__init__.py
hylite/reference/generate.py
hylite/reference/features/__init__.py
hylite/reference/spectra/__init__.py
hylite/reference/spectra/custom/__init__.py
hylite/reference/spectra/pvc/PVC_Black.txt
hylite/reference/spectra/pvc/PVC_Grey.txt
hylite/reference/spectra/pvc/PVC_Red.txt
hylite/reference/spectra/pvc/PVC_White.txt
hylite/reference/spectra/pvc/__init__.py
hylite/reference/spectra/spectralon/R50.txt
hylite/reference/spectra/spectralon/R55_SiSu.txt
hylite/reference/spectra/spectralon/R6.txt
hylite/reference/spectra/spectralon/R90.txt
hylite/reference/spectra/spectralon/__init__.py
hylite/sensors/__init__.py
hylite/sensors/fenix.py
hylite/sensors/fx.py
hylite/sensors/owl.py
hylite/sensors/rikola.py
hylite/sensors/sensor.py
hylite/sensors/calibration_data/__init__.py
hylite/sensors/calibration_data/fenix/Radiometric_2x2_1x1.dat
hylite-1.36.dist-info/licenses/LICENSE
hylite-1.36.dist-info/METADATA
hylite-1.36.dist-info/WHEEL
hylite-1.36.dist-info/top_level.txt
hylite-1.36.dist-info/RECORD
